{
    "type": "spline",
        "spline": {
            "coordinate": "jy_overworld:global/2d_channel/continental_edge_perturbance",
            "points": [
                { 
                    "location": -1.0, //lowest possible point, placeholder 
                    "value": -2, 
                    "derivative": 0 
                },{ 
                    "location": -0.6, // abyssal plain
                    "value": -1, 
                    "derivative": 0 
                },{ 
                    "location": -0.32, // continental shelf
                    "value": -0.9,
                    "derivative": 0 
                },{ 
                    "location": -0.3, // continental shelf edge
                    "value": {
                        "coordinate": "jy_overworld:global/2d_channel/hills_perturbance",
                        "points": [
                            {
                                "location": -1,
                                "value": -0.9,
                                "derivative": 0.0
                            },{
                                "location": -0.9,
                                "value": -0.8,
                                "derivative": 0.0
                            },{
                                "location": -0.4,
                                "value": -0.5,
                                "derivative": 0.0
                            },{
                                "location": -0.11,
                                "value": -0.9,
                                "derivative": 0.0
                            },{
                                "location": 0,
                                "value": -0.4,
                                "derivative": 0.0
                            },{
                                "location": 0.4,
                                "value": -0.7,
                                "derivative": 0.0
                            },{
                                "location": 0.9,
                                "value": -0.9,
                                "derivative": 0.0
                            },{
                                "location": 1,
                                "value": -0.2,
                                "derivative": 0.0
                            }
                        ]
                    },  
                    "derivative": 0 
                },{ 
                    "location": -0.23, // lower beach
                    "value": -0.2, 
                    "derivative": 0
                },{ 
                    "location": 0, // zero
                    "value": 0, 
                    "derivative": 0 
                },{ 
                    "location": 0.01, // upper beach
                    "value": 0.008, 
                    "derivative": 0 
                },{ 
                    "location": 0.12, // upper beach
                    "value": 0.1, 
                    "derivative": 0 
                },{ 
                    "location": 0.13, // upper beach erosion edge
                    "value": 0.2, 
                    "derivative": 0 
                },{ 
                    "location": 0.21, // beachside flats 
                    "value": 0.3, 
                    "derivative": 0 
                },{ 
                    "location": 1.0, // highest possible point, placeholder
                    "value": 2, 
                    "derivative": 0 
                }
            ]
        }
}